securaops_mcp_marketplace/__init__.py
securaops_mcp_marketplace/discord_connector.cp313-win_amd64.pyd
securaops_mcp_marketplace/discord_mcp_server.cp313-win_amd64.pyd
securaops_mcp_marketplace/github_connector.cp313-win_amd64.pyd
securaops_mcp_marketplace/google_drive_connector.cp313-win_amd64.pyd
securaops_mcp_marketplace/jira_connector.cp313-win_amd64.pyd
securaops_mcp_marketplace/license_manager.cp313-win_amd64.pyd
securaops_mcp_marketplace/linear_connector.cp313-win_amd64.pyd
securaops_mcp_marketplace/mongodb_connector.cp313-win_amd64.pyd
securaops_mcp_marketplace/notion_connector.cp313-win_amd64.pyd
securaops_mcp_marketplace/postgresql_connector.cp313-win_amd64.pyd
securaops_mcp_marketplace/slack_connector.cp313-win_amd64.pyd
securaops_mcp_marketplace/trello_connector.cp313-win_amd64.pyd
securaops_mcp_marketplace/version.cp313-win_amd64.pyd
securaops_mcp_marketplace-0.1.0.post6.dist-info/licenses/LICENSE
securaops_mcp_marketplace-0.1.0.post6.dist-info/METADATA
securaops_mcp_marketplace-0.1.0.post6.dist-info/WHEEL
securaops_mcp_marketplace-0.1.0.post6.dist-info/top_level.txt
securaops_mcp_marketplace-0.1.0.post6.dist-info/RECORD
