Metadata-Version: 2.4
Name: securaops-mcp-marketplace
Version: 0.1.0.post6
Summary: A marketplace for MCP (Model Context Protocol) connectors
Home-page: https://github.com/securacoder/mcp-marketplace/sdks
Author: Nephthali Djabon Tchounda
Author-email: Nephthali Djabon Tchounda <securaops5@gmail.com>
License: SecuraOps MCP Marketplace SDK
Project-URL: Homepage, https://github.com/securacoder/mcp-marketplace/sdks
Project-URL: Documentation, https://github.com/securacoder/mcp-marketplace/sdks#readme
Project-URL: Repository, https://github.com/securacoder/mcp-marketplace
Project-URL: Issues, https://github.com/securacoder/mcp-marketplace/issues
Keywords: mcp,slack,connector,llm,api
Classifier: License :: OSI Approved :: BSD License
Classifier: License :: Other/Proprietary License
Classifier: Development Status :: 4 - Beta
Classifier: Intended Audience :: Developers
Classifier: Topic :: Software Development :: Libraries
Classifier: Programming Language :: Python :: 3
Classifier: Programming Language :: Python :: 3.8
Classifier: Programming Language :: Python :: 3.9
Classifier: Programming Language :: Python :: 3.10
Classifier: Programming Language :: Python :: 3.11
Classifier: Programming Language :: Python :: 3.12
Requires-Python: >=3.8
License-File: LICENSE
Requires-Dist: requests>=2.28.0
Requires-Dist: mcp>=1.0.0
Requires-Dist: discord.py>=2.3.0
Requires-Dist: pydantic>=1.10.0
Requires-Dist: asyncpg>=0.10.0
Requires-Dist: pymongo>=4.13.0
Provides-Extra: dev
Requires-Dist: pytest; extra == "dev"
Requires-Dist: black; extra == "dev"
Requires-Dist: flake8; extra == "dev"
Requires-Dist: mypy; extra == "dev"
Dynamic: author
Dynamic: home-page
Dynamic: license-file
Dynamic: requires-python
